./.gitignore
./LICENSE
./README.md
./README.rst
./README_es.md
./README_es.rst
./pyproject.toml
./django_analytics_simple/__init__.py
./django_analytics_simple/admin.py
./django_analytics_simple/apps.py
./django_analytics_simple/middleware.py
./django_analytics_simple/models.py
./django_analytics_simple/data/GeoLite2-City.mmdb
django_analytics_simple-2024.0.9.dist-info/METADATA
django_analytics_simple-2024.0.9.dist-info/WHEEL
django_analytics_simple-2024.0.9.dist-info/licenses/LICENSE
django_analytics_simple-2024.0.9.dist-info/RECORD
