Metadata-Version: 2.3
Name: django_analytics_simple
Version: 2024.0.9
Summary: Django Analytics simple is a package designed to facilitate tracking and analysis of data in Django web applications
Project-URL: Repository, https://github.com/h4cker54n/django_analytics_simple
Author-email: Santiago Nestor Britos <s.britos@hotmail.com>
License: Creative Commons License
License-File: LICENSE
Keywords: Analytics,Application Development,Browser,Data,Database,Device,Django,Geographical Location,Informed Decisions,Maintenance,Middleware,Operating System,Table,Tracking,User,User Experience
Classifier: Framework :: Django
Classifier: Operating System :: OS Independent
Classifier: Programming Language :: Python :: 3
Requires-Python: >=3.0
Requires-Dist: django>3.0
Requires-Dist: maxminddb>2.0.0
Requires-Dist: user-agents>2.0.0
